heartbeatpy/__init__.py
heartbeatpy/calculate_votes.py
heartbeatpy-0.2.0.dist-info/LICENSE
heartbeatpy-0.2.0.dist-info/METADATA
heartbeatpy-0.2.0.dist-info/WHEEL
heartbeatpy-0.2.0.dist-info/RECORD
