Metadata-Version: 2.1
Name: heartbeatpy
Version: 0.2.0
Summary: Heartbeat survey analysis in python
License: GPL-3.0-or-later
Author: Kirsty Weitzel
Author-email: kweitzel@rti.org
Requires-Python: >=3.8,<4.0
Classifier: License :: OSI Approved :: GNU General Public License v3 or later (GPLv3+)
Classifier: Programming Language :: Python :: 3
Classifier: Programming Language :: Python :: 3.8
Classifier: Programming Language :: Python :: 3.9
Classifier: Programming Language :: Python :: 3.10
Classifier: Programming Language :: Python :: 3.11
Requires-Dist: altair (>=5.1.2,<6.0.0)
Requires-Dist: pandas (>=2.0.2,<3.0.0)
